{
    "key": "group_647cdcc4c1689",
    "title": "LC Hero - 1 Image",
    "fields": [
        {
            "key": "field_647cdcc4c557b",
            "label": "LC Hero - 1 Image",
            "name": "",
            "aria-label": "",
            "type": "message",
            "instructions": "",
            "required": 0,
            "conditional_logic": 0,
            "wrapper": {
                "width": "",
                "class": "",
                "id": ""
            },
            "message": "",
            "new_lines": "wpautop",
            "esc_html": 0
        },
        {
            "key": "field_647cdcc4c9213",
            "label": "Left",
            "name": "",
            "aria-label": "",
            "type": "tab",
            "instructions": "",
            "required": 0,
            "conditional_logic": 0,
            "wrapper": {
                "width": "",
                "class": "",
                "id": ""
            },
            "placement": "top",
            "endpoint": 0
        },
        {
            "key": "field_647cdcc4ccea9",
            "label": "Title",
            "name": "title",
            "aria-label": "",
            "type": "text",
            "instructions": "Wrap text in span tags to embolden",
            "required": 0,
            "conditional_logic": 0,
            "wrapper": {
                "width": "",
                "class": "",
                "id": ""
            },
            "default_value": "",
            "maxlength": "",
            "placeholder": "",
            "prepend": "",
            "append": ""
        },
        {
            "key": "field_647cdcc4d0b16",
            "label": "Intro",
            "name": "intro",
            "aria-label": "",
            "type": "wysiwyg",
            "instructions": "",
            "required": 0,
            "conditional_logic": 0,
            "wrapper": {
                "width": "",
                "class": "",
                "id": ""
            },
            "default_value": "",
            "tabs": "all",
            "toolbar": "full",
            "media_upload": 1,
            "delay": 0
        },
        {
            "key": "field_647cdcc4d47c1",
            "label": "CTA",
            "name": "cta",
            "aria-label": "",
            "type": "link",
            "instructions": "",
            "required": 0,
            "conditional_logic": 0,
            "wrapper": {
                "width": "66",
                "class": "",
                "id": ""
            },
            "return_format": "array"
        },
        {
            "key": "field_647cdcc4d843c",
            "label": "CTA Style",
            "name": "cta_style",
            "aria-label": "",
            "type": "radio",
            "instructions": "",
            "required": 0,
            "conditional_logic": 0,
            "wrapper": {
                "width": "33",
                "class": "",
                "id": ""
            },
            "choices": {
                "secondary": "Green",
                "primary": "Blue",
                "outline": "Outline"
            },
            "default_value": "secondary : Green",
            "return_format": "value",
            "allow_null": 0,
            "other_choice": 0,
            "layout": "vertical",
            "save_other_choice": 0
        },
        {
            "key": "field_647cdcc4dc0e0",
            "label": "CTA 2",
            "name": "cta_2",
            "aria-label": "",
            "type": "link",
            "instructions": "",
            "required": 0,
            "conditional_logic": 0,
            "wrapper": {
                "width": "66",
                "class": "",
                "id": ""
            },
            "return_format": "array"
        },
        {
            "key": "field_647cdcc4dfd7a",
            "label": "CTA 2 Style",
            "name": "cta_2_style",
            "aria-label": "",
            "type": "radio",
            "instructions": "",
            "required": 0,
            "conditional_logic": 0,
            "wrapper": {
                "width": "33",
                "class": "",
                "id": ""
            },
            "choices": {
                "secondary": "Green",
                "primary": "Blue",
                "outline": "Outline"
            },
            "default_value": "outline : Outline",
            "return_format": "value",
            "allow_null": 0,
            "other_choice": 0,
            "layout": "vertical",
            "save_other_choice": 0
        },
        {
            "key": "field_647cdcc4e3a0f",
            "label": "Right",
            "name": "",
            "aria-label": "",
            "type": "tab",
            "instructions": "",
            "required": 0,
            "conditional_logic": 0,
            "wrapper": {
                "width": "",
                "class": "",
                "id": ""
            },
            "placement": "top",
            "endpoint": 0
        },
        {
            "key": "field_647cdcc4e766d",
            "label": "Image 1",
            "name": "image_1",
            "aria-label": "",
            "type": "image",
            "instructions": "",
            "required": 0,
            "conditional_logic": 0,
            "wrapper": {
                "width": "",
                "class": "",
                "id": ""
            },
            "return_format": "id",
            "library": "all",
            "min_width": "",
            "min_height": "",
            "min_size": "",
            "max_width": "",
            "max_height": "",
            "max_size": "",
            "mime_types": "",
            "preview_size": "medium"
        }
    ],
    "location": [
        [
            {
                "param": "block",
                "operator": "==",
                "value": "acf\/lc-secondary-hero"
            }
        ]
    ],
    "menu_order": 0,
    "position": "normal",
    "style": "default",
    "label_placement": "top",
    "instruction_placement": "label",
    "hide_on_screen": "",
    "active": true,
    "description": "",
    "show_in_rest": 0,
    "modified": 1685904863
}